{
   "balance":100,
   "entries":[
      {
         "id":"12345678900",
         "email":"arden.townson@example.site",
         "ip_address":"",
         "username":"",
         "password":"",
         "hashed_password":"",
         "name":"Arden Townson",
         "vin":"",
         "address":"1095 Richterite Way, Bainville, MT 59212",
         "phone":"",
         "database_name":"covve"
      },
      {
         "id":"12345678901",
         "email":"nella.chojnowski@example.site",
         "ip_address":"",
         "username":"nella.chojnowski",
         "password":"oLae9ez9G",
         "hashed_password":"",
         "name":"",
         "vin":"",
         "address":"",
         "phone":"",
         "database_name":"AntiPublic"
      },
      {
         "id":"12345678902",
         "email":"suzi.wigdor@example.site",
         "ip_address":"",
         "username":"suziwigdor",
         "password":"eejae6Pae4u",
         "hashed_password":"",
         "name":"",
         "vin":"",
         "address":"",
         "phone":"",
         "database_name":"Collections"
      },
      {
         "id":"12345678903",
         "email":"suzi.wigdor@example.site",
         "ip_address":"",
         "username":"suziwigdor",
         "password":"eejae6Pae4u",
         "hashed_password":"",
         "name":"",
         "vin":"",
         "address":"",
         "phone":"",
         "database_name":"AntiPublic"
      },
      {
         "id":"12345678904",
         "email":"danny.manchester@example.site",
         "ip_address":"",
         "username":"dmann75",
         "password":"rah2zae3Eo",
         "hashed_password":"",
         "name":"",
         "vin":"",
         "address":"",
         "phone":"",
         "database_name":"Collections"
      },
      {
         "id":"12345678905",
         "email":"danny.manchester@example.site",
         "ip_address":"",
         "username":"dmann75",
         "password":"aiKeeliL8qu",
         "hashed_password":"",
         "name":"",
         "vin":"",
         "address":"",
         "phone":"",
         "database_name":"Adobe"
      },
      {
         "id":"12345678906",
         "email":"manuel.dahlen@example.site",
         "ip_address":"",
         "username":"dahlennn",
         "password":"",
         "hashed_password":"",
         "name":"",
         "vin":"",
         "address":"",
         "phone":"",
         "database_name":"Adobe"
      }
   ],
   "success":true,
   "took":"82µs",
   "total":7
}